Workbook

Sheet LEEME
A1: EQUIPA · CATÁLOGO MAESTRO — modelo de costos de importación
A3: Qué es: los 39 SKUs del catálogo con su costo real de importación (FOB → flete → arancel → aterrizado) y la utilidad por pieza a precio de mayoreo y menudeo.
A5: CÓMO USAR:
A6: 1. Celdas AZULES con fondo AMARILLO = se editan (parámetros, FOB, precios). Todo lo demás son fórmulas: NO tocar.
A7: 2. Cambia un parámetro en PARAMETROS (ej. arancel 25%→35%) y todo el catálogo se recalcula.
A8: 3. Columna 'Dato' en CATALOGO: [V] = FOB tomado de listado real verificable (URL en 'Fuente') · [E] = estimación de la investigación.
A9: Los [E] se vuelven [V] cuando el proveedor responda el RFQ (ventas/rfq-proveedores.md) con cotización formal.
A10: 4. CONTENEDOR simula el primer 40'HQ: edita cantidades (azul) y revisa que el CBM no pase el límite.
A11: 5. COMPETENCIA: las 465 piezas de mobiliarioenmexico.com.mx por categoría, para validar precios de venta.
A13: Fuentes de parámetros: investigacion/sourcing-china.md y mercado-mexico.md (flete Efanda/Sino-Shipping ago-2026; arancel decreto DOF 29-dic-2025; DTA/agente Camtom y DTD Express). El IGI exacto por fracción lo confirma el agente aduanal.
A14: Generado: 20-ago-2026 · se regenera con investigacion/armar_excel.py

Sheet PARAMETROS
A1: PARÁMETROS DEL MODELO (editar en azul)
A3: Tipo de cambio MXN/USD | B3: 18.5 | C3: Ajustar al día de la operación
A4: Flete marítimo 40'HQ China→Manzanillo (USD) | B4: 5000 | C4: Rango ago-2026: $3,500–5,500 (Efanda/Sino-Shipping). Cotizar en firme
A5: Seguro (% sobre FOB) | B5: 0.003 | C5: ~0.3% típico
A6: IGI / arancel (% sobre CIF) | B6: 0.3 | C6: Decreto DOF 29-dic-2025: muebles cap. 94 quedaron en 25–35% según fracción. 30% = escenario medio. CONFIRMAR por fracción con agente aduanal
A7: DTA (% sobre CIF) | B7: 0.008 | C7: 8 al millar, sin tope
A8: Agente aduanal + prevalidación + maniobras (USD/contenedor) | B8: 900 | C8: MXN $3,500–8,000 + gastos; escenario medio
A9: Flete Manzanillo→Morelia contenedor (USD) | B9: 1800 | C9: ~MXN $25,000–40,000 [E]
A10: CBM útil por 40'HQ | B10: 67 | C10: Nominal 76 CBM; 67 realista con estiba mixta
A11: IVA importación (acreditable) | B11: 0.16 | C11: Sobre CIF+IGI+DTA. Es flujo, no costo, si facturas — por eso NO entra al costo aterrizado

Sheet CATALOGO
A1: SKU | B1: Producto | C1: Categoría | D1: FOB USD/ud | E1: CBM/ud | F1: Uds por 40'HQ | G1: Flete USD/ud | H1: Seguro USD | I1: CIF USD | J1: IGI USD | K1: DTA USD | L1: Fijos USD/ud | M1: Aterrizado USD | N1: Aterrizado MXN | O1: Precio mayoreo MXN | P1: Precio menudeo MXN | Q1: Utilidad may. $ | R1: Margen may. % | S1: Utilidad men. $ | T1: Margen men. % | U1: MOQ prov. | V1: Dato | W1: Fuente FOB (URL)
A2: EQP-101 | B2: Silla Marfil | C2: sillas | D2: 26 | E2: 0.12 | F2: =ROUNDDOWN(PARAMETROS!$B$10/E2,0) | G2: =PARAMETROS!$B$4/F2 | H2: =D2*PARAMETROS!$B$5 | I2: =D2+G2+H2 | J2: =I2*PARAMETROS!$B$6 | K2: =I2*PARAMETROS!$B$7 | L2: =(PARAMETROS!$B$8+PARAMETROS!$B$9)/F2 | M2: =I2+J2+K2+L2 | N2: =M2*PARAMETROS!$B$3 | O2: 1490 | P2: 1790 | Q2: =O2-N2 | R2: =IF(O2=0,0,Q2/O2) | S2: =P2-N2 | T2: =IF(P2=0,0,S2/P2) | U2: 100-200 | V2: [V] | W2: Tianjin Okay Int'l — tianjinokayfurniture.en.made-in-china.com (velvet metal $24-26 a 200+)
A3: EQP-102 | B3: Silla Roble | C3: sillas | D3: 30 | E3: 0.17 | F3: =ROUNDDOWN(PARAMETROS!$B$10/E3,0) | G3: =PARAMETROS!$B$4/F3 | H3: =D3*PARAMETROS!$B$5 | I3: =D3+G3+H3 | J3: =I3*PARAMETROS!$B$6 | K3: =I3*PARAMETROS!$B$7 | L3: =(PARAMETROS!$B$8+PARAMETROS!$B$9)/F3 | M3: =I3+J3+K3+L3 | N3: =M3*PARAMETROS!$B$3 | O3: 1890 | P3: 2290 | Q3: =O3-N3 | R3: =IF(O3=0,0,Q3/O3) | S3: =P3-N3 | T3: =IF(P3=0,0,S3/P3) | U3: 200 | V3: [V] | W3: Qingdao Welhome — welhome.en.made-in-china.com (bentwood haya $25-38)
A4: EQP-103 | B4: Silla Nube | C4: sillas | D4: 12 | E4: 0.08 | F4: =ROUNDDOWN(PARAMETROS!$B$10/E4,0) | G4: =PARAMETROS!$B$4/F4 | H4: =D4*PARAMETROS!$B$5 | I4: =D4+G4+H4 | J4: =I4*PARAMETROS!$B$6 | K4: =I4*PARAMETROS!$B$7 | L4: =(PARAMETROS!$B$8+PARAMETROS!$B$9)/F4 | M4: =I4+J4+K4+L4 | N4: =M4*PARAMETROS!$B$3 | O4: 890 | P4: 1090 | Q4: =O4-N4 | R4: =IF(O4=0,0,Q4/O4) | S4: =P4-N4 | T4: =IF(P4=0,0,S4/P4) | U4: 50-100 | V4: [V] | W4: Beijing Jinyang $9-16 / Langfang Airun $13-17 (made-in-china.com)
A5: EQP-104 | B5: Silla Prado | C5: sillas | D5: 28 | E5: 0.12 | F5: =ROUNDDOWN(PARAMETROS!$B$10/E5,0) | G5: =PARAMETROS!$B$4/F5 | H5: =D5*PARAMETROS!$B$5 | I5: =D5+G5+H5 | J5: =I5*PARAMETROS!$B$6 | K5: =I5*PARAMETROS!$B$7 | L5: =(PARAMETROS!$B$8+PARAMETROS!$B$9)/F5 | M5: =I5+J5+K5+L5 | N5: =M5*PARAMETROS!$B$3 | O5: 1590 | P5: 1890 | Q5: =O5-N5 | R5: =IF(O5=0,0,Q5/O5) | S5: =P5-N5 | T5: =IF(P5=0,0,S5/P5) | U5: 100 | V5: [V] | W5: Tianjin Okay / Zhuoguan $20.90-29.90 (made-in-china.com)
A6: EQP-105 | B6: Silla Vega | C6: sillas | D6: 35 | E6: 0.17 | F6: =ROUNDDOWN(PARAMETROS!$B$10/E6,0) | G6: =PARAMETROS!$B$4/F6 | H6: =D6*PARAMETROS!$B$5 | I6: =D6+G6+H6 | J6: =I6*PARAMETROS!$B$6 | K6: =I6*PARAMETROS!$B$7 | L6: =(PARAMETROS!$B$8+PARAMETROS!$B$9)/F6 | M6: =I6+J6+K6+L6 | N6: =M6*PARAMETROS!$B$3 | O6: 1990 | P6: 2390 | Q6: =O6-N6 | R6: =IF(O6=0,0,Q6/O6) | S6: =P6-N6 | T6: =IF(P6=0,0,S6/P6) | U6: 100 | V6: [E] | W6: Interpolado Welhome/CDG (madera+tapiz)
A7: EQP-106 | B7: Silla Terra | C7: sillas | D7: 31 | E7: 0.13 | F7: =ROUNDDOWN(PARAMETROS!$B$10/E7,0) | G7: =PARAMETROS!$B$4/F7 | H7: =D7*PARAMETROS!$B$5 | I7: =D7+G7+H7 | J7: =I7*PARAMETROS!$B$6 | K7: =I7*PARAMETROS!$B$7 | L7: =(PARAMETROS!$B$8+PARAMETROS!$B$9)/F7 | M7: =I7+J7+K7+L7 | N7: =M7*PARAMETROS!$B$3 | O7: 1990 | P7: 2490 | Q7: =O7-N7 | R7: =IF(O7=0,0,Q7/O7) | S7: =P7-N7 | T7: =IF(P7=0,0,S7/P7) | U7: 100 | V7: [V] | W7: Alibaba showroom velvet dining chair $18-31.5
A8: EQP-201 | B8: Banco Norte Alto | C8: bancos | D8: 12 | E8: 0.09 | F8: =ROUNDDOWN(PARAMETROS!$B$10/E8,0) | G8: =PARAMETROS!$B$4/F8 | H8: =D8*PARAMETROS!$B$5 | I8: =D8+G8+H8 | J8: =I8*PARAMETROS!$B$6 | K8: =I8*PARAMETROS!$B$7 | L8: =(PARAMETROS!$B$8+PARAMETROS!$B$9)/F8 | M8: =I8+J8+K8+L8 | N8: =M8*PARAMETROS!$B$3 | O8: 1190 | P8: 1390 | Q8: =O8-N8 | R8: =IF(O8=0,0,Q8/O8) | S8: =P8-N8 | T8: =IF(P8=0,0,S8/P8) | U8: 200 | V8: [V] | W8: Tianjin Kingnod BC-234BV $11-15, 5/caja — kingnodfurniture.en.made-in-china.com
A9: EQP-202 | B9: Banco Ámbar | C9: bancos | D9: 14 | E9: 0.09 | F9: =ROUNDDOWN(PARAMETROS!$B$10/E9,0) | G9: =PARAMETROS!$B$4/F9 | H9: =D9*PARAMETROS!$B$5 | I9: =D9+G9+H9 | J9: =I9*PARAMETROS!$B$6 | K9: =I9*PARAMETROS!$B$7 | L9: =(PARAMETROS!$B$8+PARAMETROS!$B$9)/F9 | M9: =I9+J9+K9+L9 | N9: =M9*PARAMETROS!$B$3 | O9: 1290 | P9: 1590 | Q9: =O9-N9 | R9: =IF(O9=0,0,Q9/O9) | S9: =P9-N9 | T9: =IF(P9=0,0,S9/P9) | U9: 200 | V9: [V] | W9: Tianjin Kingnod $9.65-18.55
A10: EQP-203 | B10: Banco Cuero | C10: bancos | D10: 40 | E10: 0.3 | F10: =ROUNDDOWN(PARAMETROS!$B$10/E10,0) | G10: =PARAMETROS!$B$4/F10 | H10: =D10*PARAMETROS!$B$5 | I10: =D10+G10+H10 | J10: =I10*PARAMETROS!$B$6 | K10: =I10*PARAMETROS!$B$7 | L10: =(PARAMETROS!$B$8+PARAMETROS!$B$9)/F10 | M10: =I10+J10+K10+L10 | N10: =M10*PARAMETROS!$B$3 | O10: 2690 | P10: 3190 | Q10: =O10-N10 | R10: =IF(O10=0,0,Q10/O10) | S10: =P10-N10 | T10: =IF(P10=0,0,S10/P10) | U10: 20 | V10: [E] | W10: Serenity Made (Guangzhou), gama $40-80, 0.30 CBM [V]
A11: EQP-204 | B11: Banco Faro | C11: bancos | D11: 10 | E11: 0.09 | F11: =ROUNDDOWN(PARAMETROS!$B$10/E11,0) | G11: =PARAMETROS!$B$4/F11 | H11: =D11*PARAMETROS!$B$5 | I11: =D11+G11+H11 | J11: =I11*PARAMETROS!$B$6 | K11: =I11*PARAMETROS!$B$7 | L11: =(PARAMETROS!$B$8+PARAMETROS!$B$9)/F11 | M11: =I11+J11+K11+L11 | N11: =M11*PARAMETROS!$B$3 | O11: 1090 | P11: 1290 | Q11: =O11-N11 | R11: =IF(O11=0,0,Q11/O11) | S11: =P11-N11 | T11: =IF(P11=0,0,S11/P11) | U11: 500 | V11: [V] | W11: Langfang Bingwei $7.50-13.80 (Gold 2025 — pedir auditoría)
A12: EQP-205 | B12: Banco Eje | C12: bancos | D12: 22 | E12: 0.1 | F12: =ROUNDDOWN(PARAMETROS!$B$10/E12,0) | G12: =PARAMETROS!$B$4/F12 | H12: =D12*PARAMETROS!$B$5 | I12: =D12+G12+H12 | J12: =I12*PARAMETROS!$B$6 | K12: =I12*PARAMETROS!$B$7 | L12: =(PARAMETROS!$B$8+PARAMETROS!$B$9)/F12 | M12: =I12+J12+K12+L12 | N12: =M12*PARAMETROS!$B$3 | O12: 1490 | P12: 1690 | Q12: =O12-N12 | R12: =IF(O12=0,0,Q12/O12) | S12: =P12-N12 | T12: =IF(P12=0,0,S12/P12) | U12: 100 | V12: [V] | W12: Anji Zhenguan ZG18-019 $18-26
A13: EQP-301 | B13: Mesa Encino | C13: mesas | D13: 60 | E13: 0.2 | F13: =ROUNDDOWN(PARAMETROS!$B$10/E13,0) | G13: =PARAMETROS!$B$4/F13 | H13: =D13*PARAMETROS!$B$5 | I13: =D13+G13+H13 | J13: =I13*PARAMETROS!$B$6 | K13: =I13*PARAMETROS!$B$7 | L13: =(PARAMETROS!$B$8+PARAMETROS!$B$9)/F13 | M13: =I13+J13+K13+L13 | N13: =M13*PARAMETROS!$B$3 | O13: 3190 | P13: 3690 | Q13: =O13-N13 | R13: =IF(O13=0,0,Q13/O13) | S13: =P13-N13 | T13: =IF(P13=0,0,S13/P13) | U13: 20 | V13: [V] | W13: Zhongshan Uptop $30-80 / Foshan Ron $39.90-139
... A40: EQP-962 | B40: Set Jardín Blanco | C40: exterior | D40: 65 | E40: 0.3 | F40: =ROUNDDOWN(PARAMETROS!$B$10/E40,0) | G40: =PARAMETROS!$B$4/F40 | H40: =D40*PARAMETROS!$B$5 | I40: =D40+G40+H40 | J40: =I40*PARAMETROS!$B$6 | K40: =I40*PARAMETROS!$B$7 | L40: =(PARAMETROS!$B$8+PARAMETROS!$B$9)/F40 | M40: =I40+J40+K40+L40 | N40: =M40*PARAMETROS!$B$3 | O40: 3690 | P40: 4290 | Q40: =O40-N40 | R40: =IF(O40=0,0,Q40/O40) | S40: =P40-N40 | T40: =IF(P40=0,0,S40/P40) | U40: 5 sets | V40: [V] | W40: Linyi Gaotong
B42: Fijos USD/ud = (agente aduanal + flete interno) prorrateados entre las unidades del contenedor si fuera monoproducto; en mezcla real el prorrateo va por CBM (ver CONTENEDOR). IVA de importación no incluido en el costo: es acreditable (PARAMETROS!B11).

Sheet CONTENEDOR
A1: SIMULADOR · PRIMER CONTENEDOR 40'HQ (edita cantidades en azul)
A3: SKU | B3: Producto | C3: Cantidad | D3: CBM total | E3: Inversión aterrizada MXN | F3: Venta mayoreo MXN | G3: Utilidad MXN
A4: EQP-102 | B4: =INDEX(CATALOGO!B:B,MATCH(A4,CATALOGO!A:A,0)) | C4: 200 | D4: =C4*INDEX(CATALOGO!E:E,MATCH(A4,CATALOGO!A:A,0)) | E4: =C4*INDEX(CATALOGO!N:N,MATCH(A4,CATALOGO!A:A,0)) | F4: =C4*INDEX(CATALOGO!O:O,MATCH(A4,CATALOGO!A:A,0)) | G4: =F4-E4
A5: EQP-105 | B5: =INDEX(CATALOGO!B:B,MATCH(A5,CATALOGO!A:A,0)) | C5: 100 | D5: =C5*INDEX(CATALOGO!E:E,MATCH(A5,CATALOGO!A:A,0)) | E5: =C5*INDEX(CATALOGO!N:N,MATCH(A5,CATALOGO!A:A,0)) | F5: =C5*INDEX(CATALOGO!O:O,MATCH(A5,CATALOGO!A:A,0)) | G5: =F5-E5
A6: EQP-101 | B6: =INDEX(CATALOGO!B:B,MATCH(A6,CATALOGO!A:A,0)) | C6: 60 | D6: =C6*INDEX(CATALOGO!E:E,MATCH(A6,CATALOGO!A:A,0)) | E6: =C6*INDEX(CATALOGO!N:N,MATCH(A6,CATALOGO!A:A,0)) | F6: =C6*INDEX(CATALOGO!O:O,MATCH(A6,CATALOGO!A:A,0)) | G6: =F6-E6
A7: EQP-103 | B7: =INDEX(CATALOGO!B:B,MATCH(A7,CATALOGO!A:A,0)) | C7: 100 | D7: =C7*INDEX(CATALOGO!E:E,MATCH(A7,CATALOGO!A:A,0)) | E7: =C7*INDEX(CATALOGO!N:N,MATCH(A7,CATALOGO!A:A,0)) | F7: =C7*INDEX(CATALOGO!O:O,MATCH(A7,CATALOGO!A:A,0)) | G7: =F7-E7
A8: EQP-201 | B8: =INDEX(CATALOGO!B:B,MATCH(A8,CATALOGO!A:A,0)) | C8: 60 | D8: =C8*INDEX(CATALOGO!E:E,MATCH(A8,CATALOGO!A:A,0)) | E8: =C8*INDEX(CATALOGO!N:N,MATCH(A8,CATALOGO!A:A,0)) | F8: =C8*INDEX(CATALOGO!O:O,MATCH(A8,CATALOGO!A:A,0)) | G8: =F8-E8
A9: EQP-202 | B9: =INDEX(CATALOGO!B:B,MATCH(A9,CATALOGO!A:A,0)) | C9: 40 | D9: =C9*INDEX(CATALOGO!E:E,MATCH(A9,CATALOGO!A:A,0)) | E9: =C9*INDEX(CATALOGO!N:N,MATCH(A9,CATALOGO!A:A,0)) | F9: =C9*INDEX(CATALOGO!O:O,MATCH(A9,CATALOGO!A:A,0)) | G9: =F9-E9
A10: EQP-301 | B10: =INDEX(CATALOGO!B:B,MATCH(A10,CATALOGO!A:A,0)) | C10: 40 | D10: =C10*INDEX(CATALOGO!E:E,MATCH(A10,CATALOGO!A:A,0)) | E10: =C10*INDEX(CATALOGO!N:N,MATCH(A10,CATALOGO!A:A,0)) | F10: =C10*INDEX(CATALOGO!O:O,MATCH(A10,CATALOGO!A:A,0)) | G10: =F10-E10
A11: EQP-302 | B11: =INDEX(CATALOGO!B:B,MATCH(A11,CATALOGO!A:A,0)) | C11: 40 | D11: =C11*INDEX(CATALOGO!E:E,MATCH(A11,CATALOGO!A:A,0)) | E11: =C11*INDEX(CATALOGO!N:N,MATCH(A11,CATALOGO!A:A,0)) | F11: =C11*INDEX(CATALOGO!O:O,MATCH(A11,CATALOGO!A:A,0)) | G11: =F11-E11
A12: EQP-404 | B12: =INDEX(CATALOGO!B:B,MATCH(A12,CATALOGO!A:A,0)) | C12: 10 | D12: =C12*INDEX(CATALOGO!E:E,MATCH(A12,CATALOGO!A:A,0)) | E12: =C12*INDEX(CATALOGO!N:N,MATCH(A12,CATALOGO!A:A,0)) | F12: =C12*INDEX(CATALOGO!O:O,MATCH(A12,CATALOGO!A:A,0)) | G12: =F12-E12
A13: EQP-401 | B13: =INDEX(CATALOGO!B:B,MATCH(A13,CATALOGO!A:A,0)) | C13: 8 | D13: =C13*INDEX(CATALOGO!E:E,MATCH(A13,CATALOGO!A:A,0)) | E13: =C13*INDEX(CATALOGO!N:N,MATCH(A13,CATALOGO!A:A,0)) | F13: =C13*INDEX(CATALOGO!O:O,MATCH(A13,CATALOGO!A:A,0)) | G13: =F13-E13
A14: EQP-601 | B14: =INDEX(CATALOGO!B:B,MATCH(A14,CATALOGO!A:A,0)) | C14: 6 | D14: =C14*INDEX(CATALOGO!E:E,MATCH(A14,CATALOGO!A:A,0)) | E14: =C14*INDEX(CATALOGO!N:N,MATCH(A14,CATALOGO!A:A,0)) | F14: =C14*INDEX(CATALOGO!O:O,MATCH(A14,CATALOGO!A:A,0)) | G14: =F14-E14
A15: EQP-802 | B15: =INDEX(CATALOGO!B:B,MATCH(A15,CATALOGO!A:A,0)) | C15: 30 | D15: =C15*INDEX(CATALOGO!E:E,MATCH(A15,CATALOGO!A:A,0)) | E15: =C15*INDEX(CATALOGO!N:N,MATCH(A15,CATALOGO!A:A,0)) | F15: =C15*INDEX(CATALOGO!O:O,MATCH(A15,CATALOGO!A:A,0)) | G15: =F15-E15
... A20: EQP-960 | B20: =INDEX(CATALOGO!B:B,MATCH(A20,CATALOGO!A:A,0)) | C20: 16 | D20: =C20*INDEX(CATALOGO!E:E,MATCH(A20,CATALOGO!A:A,0)) | E20: =C20*INDEX(CATALOGO!N:N,MATCH(A20,CATALOGO!A:A,0)) | F20: =C20*INDEX(CATALOGO!O:O,MATCH(A20,CATALOGO!A:A,0)) | G20: =F20-E20
B22: TOTAL | C22: =SUM(C4:C20) | D22: =SUM(D4:D20) | E22: =SUM(E4:E20) | F22: =SUM(F4:F20) | G22: =SUM(G4:G20)
B23: CBM disponible (PARAMETROS!B10) | D23: =PARAMETROS!$B$10
B24: ¿Cabe? (CBM total ≤ disponible) | D24: =IF(D22<=D23,"SÍ CABE","NO CABE — quita piezas")
B26: IVA de importación estimado (flujo acreditable, no costo): | E26: =E22*PARAMETROS!$B$11

Sheet COMPETENCIA
A1: REFERENCIA: mobiliarioenmexico.com.mx — 465 productos (descarga 20-ago-2026, datos crudos en catalogo-referencia.json)
A3: Categoría (suya) | B3: # productos | C3: Precio mín MXN | D3: Precio máx MXN
A4: Sillas Ejecutivas | B4: 82 | C4: 1490 | D4: 17890
A5: Mesas de Comedor | B5: 51 | C5: 1990 | D5: 59990
A6: Sillas de Comedor | B6: 47 | C6: 640 | D6: 3390
A7: Sillas de Visita | B7: 46 | C7: 990 | D7: 8390
A8: Sillas Operativas | B8: 40 | C8: 990 | D8: 6890
A9: Escritorio | B9: 34 | C9: 1690 | D9: 26290
A10: Bancas Tandem | B10: 19 | C10: 2990 | D10: 10490
A11: Mesas de Juntas | B11: 17 | C11: 2690 | D11: 40790
A12: Estaciones de Trabajo | B12: 17 | C12: 6490 | D12: 58590
A13: Bancos de Barra | B13: 17 | C13: 1090 | D13: 3990
A14: Sillones | B14: 17 | C14: 3290 | D14: 24990
A15: Sillones Confortables | B15: 14 | C15: 2390 | D15: 4990
... A31: Botes de Basura | B31: 1 | C31: 5990 | D31: 5990
